MANIFEST.in
README.rst
setup.py
merkyl/__init__.py
merkyl/merkyl.tpl
merkyl.egg-info/PKG-INFO
merkyl.egg-info/SOURCES.txt
merkyl.egg-info/dependency_links.txt
merkyl.egg-info/entry_points.txt
merkyl.egg-info/pbr.json
merkyl.egg-info/requires.txt
merkyl.egg-info/top_level.txt