Metadata-Version: 1.1
Name: merkyl
Version: 1.0.6
Summary: Log file tailer with bottle
Home-page: https://github.com/psav/merkyl
Author: Pete Savage
Author-email: UNKNOWN
License: MIT
Keywords: tail,linux,bottle
Platform: UNKNOWN
Classifier: Programming Language :: Python
Classifier: Development Status :: 4 - Beta
Classifier: Operating System :: POSIX :: Linux
Classifier: License :: OSI Approved :: MIT License
